gpt35/__init__.py
gpt35/gpta.py
gpt35-0.1.0.dist-info/METADATA
gpt35-0.1.0.dist-info/WHEEL
gpt35-0.1.0.dist-info/top_level.txt
gpt35-0.1.0.dist-info/RECORD
